{
  "nodes": {
    "BIOX": -0.721,
    "BBAR": 21.256,
    "BMA": 16.63,
    "GGAL": 18.842,
    "SUPV": 17.257,
    "LOMA": 7.419,
    "CRESY": 6.626,
    "AGRO": 12.189,
    "TGS": 27.847,
    "YPF": 28.992,
    "IRS": 11.213,
    "TEO": 29.083,
    "DESP": 7.246,
    "PAM": 31.573,
    "CEPU": 19.392,
    "EDN": 29.932,
    "TEAM": 5.764,
    "WDS": 12.331,
    "BHP": 7.919,
    "DCFC": -7.2,
    "NVX": -17.534,
    "IXHL": -1.376,
    "IREN": 44.966,
    "OPT": -21.397,
    "IMMP": -9.659,
    "MESO": 8.889,
    "IAF": 4.651,
    "OSW": 3.169,
    "LHC": 1.061,
    "MTLS": 2.724,
    "NYXH": 51.455,
    "EURN": 10.989,
    "BUD": 6.759,
    "GLPG": -3.495,
    "KNSA": 3.229,
    "LAZ": 2.724,
    "BBU": 11.064,
    "NTB": -14.125,
    "FLNG": 12.365,
    "FRO": 5.373,
    "GLNG": 5.38,
    "TK": 12.212,
    "TNK": 3.968,
    "DHT": -0.758,
    "VAL": 7.873,
    "BORR": 19.219,
    "NBR": 2.395,
    "SFL": 3.871,
    "SIG": -0.159,
    "ASC": 9.618,
    "GOGL": -0.835,
    "NAT": 3.784,
    "HSHP": null,
    "G": 2.455,
    "ACGL": 7.386,
    "ACGLN": 0.287,
    "ESGR": 3.733,
    "IGIC": -2.604,
    "MHLD": -3.913,
    "RE": 2.696,
    "RNR": 2.793,
    "SPNT": 28.63,
    "AGO": 8.708,
    "AXS": 2.602,
    "ESNT": 8.15,
    "JRVR": -10.558,
    "ARGO": 1.791,
    "WTM": 2.19,
    "BNRE": 11.281,
    "TGH": 14.263,
    "TRTN": 34.576,
    "BEP": 7.185,
    "BIP": 9.353,
    "LILA": 14.249,
    "LILAK": 14.213,
    "GGB": 12.271,
    "SID": 4.878,
    "TIMB": 14.133,
    "CIG": 24.188,
    "ELP": 16.564,
    "VIV": 8.632,
    "SBS": -2.355,
    "EBR": 6.047,
    "EBR-B": 9.456,
    "BRFS": -0.769,
    "SUZ": -2.735,
    "CREC": 0.24,
    "STIX": -10.491,
    "CINT": -13.755,
    "PAGS": 10.11,
    "NTCO": -13.153,
    "VSTA": 2.703,
    "VTRU": -27.362,
    "LND": 6.667,
    "ASAI": -13.839,
    "PBR": 20.858,
    "PBR-A": 21.236,
    "CSAN": 17.051,
    "UGP": 13.281,
    "SGML": 13.758,
    "VALE": 0.577,
    "ATLX": 72.185,
    "NU": -1.302,
    "BSBR": 9.02,
    "BBD": 4.494,
    "INTR": 9.877,
    "ITUB": 16.183,
    "ABEV": 8.856,
    "VINP": -3.072,
    "LVRO": -16.198,
    "GOL": -0.704,
    "ERJ": 8.202,
    "AZUL": -10.313,
    "XP": 18.057,
    "BAK": 17.847,
    "CBD": 12.915,
    "AFYA": 14.687,
    "ARCE": -13.78,
    "OGI": -13.883,
    "SNDL": -1.258,
    "ACB": -12.243,
    "BHC": -1.797,
    "CGC": -27.451,
    "CRON": -2.97,
    "ERO": 20.652,
    "HBM": 17.117,
    "IE": 12.121,
    "TGB": 15.541,
    "MEOH": 3.018,
    "TSAT": 26.788,
    "HIVE": 33.218,
    "HUT": 15.116,
    "BITF": 42.588,
    "ZYME": 23.133,
    "RPTX": -6.496,
    "XENE": 8.524,
    "MIST": 7.932,
    "EPIX": -8.143,
    "FUSN": 1.453,
    "GIL": -0.031,
    "GOOS": 0.488,
    "LULU": 23.867,
    "BAM": 6.148,
    "BN": 11.391,
    "CEF": 8.871,
    "CAE": 13.359,
    "NTR": 3.027,
    "PHYS": 4.909,
    "PSLV": 15.385,
    "SII": 4.48,
    "SPPP": 10.662,
    "MGA": 5.692,
    "WPRT": -10.499,
    "ACHV": 75.676,
    "AUPH": 12.435,
    "BCTX": 5.718,
    "BLU": -3.2,
    "VBNK": 5.556,
    "ABCL": -1.203,
    "RY": 4.692,
    "TD": 5.879,
    "BMO": 5.409,
    "BNS": 7.05,
    "CM": 3.737,
    "NMG": -18.548,
    "VZLA": 14.286,
    "WRN": 12.069,
    "ASM": 36.333,
    "EXK": 29.688,
    "GATO": 57.65,
    "GROY": 14.851,
    "MTA": 11.273,
    "MUX": 26.214,
    "NEWP": 24.091,
    "PLG": 29.412,
    "SILV": 13.167,
    "TFPM": 27.643,
    "VOXR": 17.6,
    "SKE": 21.875,
    "SLI": 18.318,
    "TECK": 42.21,
    "TMC": 5.52,
    "TMQ": 11.359,
    "USAS": 27.273,
    "LAC": -0.049,
    "LGO": 3.441,
    "NAK": 12.141,
    "AMLI": -6.531,
    "PBA": 8.94,
    "EMX": 7.853,
    "FURY": 5.263,
    "CVE": 11.251,
    "ZTEK": 5.96,
    "EFXT": 3.754,
    "NOA": 11.517,
    "ENB": 8.185,
    "IMO": 21.288,
    "SU": 10.799,
    "WFG": 6.708,
    "BGI": -0.123,
    "NVCN": 1.326,
    "PROF": -0.362,
    "PDS": 4.258,
    "BLCO": -0.793,
    "BTE": 21.148,
    "CNQ": 20.814,
    "CPG": 29.648,
    "ERF": 13.507,
    "GTE": 21.759,
    "HHRS": 42.4,
    "OBE": 11.367,
    "VET": 9.171,
    "BTG": 18.927,
    "CGAU": 19.376,
    "GLDG": 7.767,
    "GOLD": 11.322,
    "IAG": 29.237,
    "KGC": 34.726,
    "NFGC": 25.971,
    "NG": 4.643,
    "NGD": 56.269,
    "ODV": 18.08,
    "OR": 14.907,
    "ORLA": 18.75,
    "PAAS": 8.262,
    "SA": 20.395,
    "SAND": 9.701,
    "AEM": 19.348,
    "AGI": 23.563,
    "EGO": 18.307,
    "EQX": 28.675,
    "FNV": 13.322,
    "FSM": 19.255,
    "GAU": 34.977,
    "TLRY": -3.101,
    "CLS": 5.378,
    "MMAT": -55.603,
    "BRAG": -3.804,
    "IMAX": 19.907,
    "STN": 3.67,
    "LEV": -1.005,
    "THM": 5.273,
    "TRX": 15.406,
    "WPM": 14.615,
    "ALYA": 6.633,
    "GIB": 8.341,
    "SLF": 7.421,
    "MFC": 7.107,
    "EGLX": -13.413,
    "TCX": -19.153,
    "TIXT": -3.023,
    "NVEI": 0.616,
    "CSIQ": 10.975,
    "RBA": 12.031,
    "TRI": 4.926,
    "LOOP": 25.214,
    "BLDP": -1.953,
    "PYR": -24.752,
    "BB": 21.138,
    "OTEX": 6.53,
    "SHOP": 8.619,
    "DCBO": 0.156,
    "DSGX": 6.709,
    "LSPD": -3.978,
    "AG": 5.202,
    "MAG": 12.054,
    "SVM": 28.431,
    "ABST": 15.344,
    "POET": 0,
    "TRP": 12.85,
    "CNI": 3.308,
    "CP": -1.306,
    "HITI": 19.298,
    "CIGI": -3.942,
    "QSR": 10.05,
    "REAX": 0.763,
    "TCN": 2.03,
    "DOOO": -4.241,
    "MERC": -2.451,
    "FSV": 6.986,
    "FTS": 6.599,
    "AQN": 10.821,
    "AQNU": 12.645,
    "TFII": -2.017,
    "CCJ": 5.811,
    "DNN": 1.98,
    "NXE": 0.826,
    "UROY": 0.976,
    "TAC": 11.548,
    "ASTL": 0.127,
    "TU": 7.798,
    "RCI": 9.788,
    "BCE": 9.697,
    "GFL": 4.066,
    "LICY": 1.714,
    "WCN": 5.769,
    "CWCO": 17.106,
    "AHRN": 0.8,
    "BCSA": 1.861,
    "BCSAU": 0.196,
    "STNE": 21.254,
    "GLRE": -0.713,
    "FN": -13.237,
    "FDP": -1.849,
    "PAX": 4.372,
    "BGNE": 17.809,
    "TBPH": 10.458,
    "BCH": 6.367,
    "BSAC": 10.452,
    "CCU": 8.169,
    "AKO-A": 5.995,
    "AKO-B": 5.459,
    "ITCB": 6.433,
    "SQM": 12.088,
    "ENIC": 14.894,
    "RLX": 6.504,
    "TCOM": -2.247,
    "TOUR": -6.585,
    "MNSO": -9.475,
    "NAAS": 107.586,
    "BZ": -2,
    "JKS": 9.815,
    "TUYA": 1.058,
    "GCT": -4.924,
    "KC": 45.802,
    "OCFT": -9.847,
    "YMM": 1.414,
    "AIXI": 8.556,
    "API": 10.241,
    "DQ": -4.894,
    "ICG": 9.125,
    "THCH": 34.492,
    "YUMC": 4.362,
    "YI": 0,
    "GGE": 21.239,
    "BEKE": 0.221,
    "EJH": -53.18,
    "EM": -20.635,
    "YGF": null,
    "KNDI": 18.696,
    "NOAH": -3.586,
    "PUYI": -0.2,
    "CANG": 9.346,
    "LI": 18.881,
    "NIO": 15.647,
    "NIU": -1.562,
    "HSAI": -8.181,
    "XPEV": 37.215,
    "CAAS": -25.733,
    "ECX": -1.695,
    "EH": 26.265,
    "XNET": -12.69,
    "HYW": 8.451,
    "YS": -87.846,
    "ZLAB": 12.781,
    "SJ": 3.008,
    "GRCL": -0.5,
    "IMAB": 1.12,
    "CAN": -0.685,
    "TIGR": 6.472,
    "FINV": 2.895,
    "LU": 10.326,
    "LX": 7.957,
    "QD": 2.586,
    "QFIN": 13.588,
    "XYF": 23.401,
    "YRD": -20.789,
    "BNR": -3.378,
    "BEDU": -6.122,
    "DAO": -23.628,
    "EDU": 5.201,
    "GOTU": -14.014,
    "IH": 4.63,
    "QSG": -16.597,
    "STG": -6.51,
    "TAL": 8.153,
    "DDL": -1.542,
    "HOLO": 8.962,
    "HOLI": -5.045,
    "HUYA": -19.643,
    "IQ": 1.266,
    "BILI": -2.731,
    "NTES": 10.513,
    "SOHU": -0.213,
    "FANH": 2.048,
    "SFWL": null,
    "ZTO": 4.126,
    "ATHM": 1.235,
    "BIDU": -4.792,
    "DOYU": -8,
    "JFIN": 60.37,
    "MOMO": 19.326,
    "TME": 2.423,
    "ZH": 3.448,
    "BABA": 17.271,
    "BZUN": -13.757,
    "DADA": -4.219,
    "WB": 7.706,
    "WDH": 1.365,
    "VNET": 4.235,
    "CD": 3.236,
    "GDS": 5.665,
    "YSG": -15.541,
    "SY": 64.943,
    "MHUA": -66.987,
    "LANV": -3.54,
    "ATAT": -2.492,
    "GHG": 9.639,
    "HTHT": 0.632,
    "JD": -4.373,
    "RERE": -3.309,
    "VIPS": 0,
    "GDHG": null,
    "CNF": 19.556,
    "GLG": -27.928,
    "EC": 14.683,
    "GPRK": 6.055,
    "TGLS": 10.089,
    "AVAL": 20.561,
    "CIB": 25.043,
    "ESTA": 5.826,
    "ASND": -24.551,
    "GMAB": 19.245,
    "NVO": 23.169,
    "NOK": 6.127,
    "SNY": 16.168,
    "IPHA": 14.384,
    "IVA": -34.983,
    "GNFT": -7.619,
    "DBVT": 1.274,
    "NBTX": 12.821,
    "VALN": 3.196,
    "CLLS": 9.677,
    "CSTM": 1.05,
    "CRTO": 3.941,
    "EDAP": -4.933,
    "TTE": 11.762,
    "SQNS": 1.304,
    "ORAN": 9.027,
    "SSU": -24.719,
    "SAP": 5.736,
    "FMS": 17.132,
    "JMIA": -3.526,
    "MYTE": 8.696,
    "TRVG": -2.069,
    "LILM": -38.373,
    "BNTX": -5.464,
    "ATAI": 56,
    "AFMD": 5.513,
    "DB": 4.554,
    "IFRX": 130.601,
    "IMTX": -13.307,
    "CVAC": 14.08,
    "MOR": 30.025,
    "EVO": 8.833,
    "MYNA": -6.25,
    "SBLK": 3.882,
    "CPLP": 8.273,
    "DAC": 12.533,
    "DSX": 6.51,
    "ESEA": 12.216,
    "GASS": 5.556,
    "SHIP": -10.32,
    "TNP": 6.4,
    "GLOP": 4.439,
    "TOP": 14.487,
    "PRE": 0.726,
    "HCM": 13.208,
    "RGC": -0.753,
    "FUTU": 6.654,
    "AMTD": 15.232,
    "TROO": 45.307,
    "HKD": -8.24,
    "SIMO": 0.294,
    "OPA": 0.196,
    "BSAQ": 0.589,
    "BTWN": 0.1,
    "BTWNU": -0.739,
    "MLCO": 11.942,
    "MSC": 26.354,
    "UCL": -7.342,
    "SIFY": 7.407,
    "YTRA": 7.254,
    "MMYT": -5.065,
    "AZRE": 24.623,
    "HDB": 7.497,
    "IBN": 9.926,
    "RDY": 10.588,
    "INFY": -11.635,
    "WIT": -5.64,
    "WNS": -0.927,
    "TLK": 7.311,
    "AER": 5.282,
    "ALLE": -1.648,
    "ETN": -0.803,
    "AON": 10.297,
    "ACN": 10.699,
    "ADSE": -16.538,
    "DOLE": 4.901,
    "STE": 5.271,
    "MDT": 3.595,
    "PDD": -27.052,
    "PRGO": 3.166,
    "ALKS": 10.345,
    "AMYT": 0.616,
    "AVDL": 10.891,
    "HZNP": 2.199,
    "AMRN": -14.724,
    "ICLR": 0.309,
    "STX": 4.984,
    "JHX": 10.829,
    "JCI": -2.052,
    "TT": -2.589,
    "CRH": 1.514,
    "PRTA": 8.801,
    "JAZZ": 6.347,
    "GHRS": 2.081,
    "APTV": -4.074,
    "CMPR": 29.646,
    "RYAAY": 6.28,
    "ADNT": -2.722,
    "INVZ": -25.897,
    "ICL": -3.464,
    "TRMR": 15.356,
    "ESLT": 2.061,
    "MBLY": -0.324,
    "DRTS": 1.987,
    "MDWD": 18.779,
    "SLGL": 9.425,
    "CSTE": -16.018,
    "NNDM": -3.065,
    "SILC": -2.176,
    "GILT": -12.774,
    "ITRN": -2.759,
    "AUDC": -28.117,
    "CRNT": 0.595,
    "KMDA": 6.621,
    "NNOX": -8.571,
    "ZIM": -12.108,
    "INMD": 19.165,
    "WILC": 4.252,
    "NGMS": -2.749,
    "SHLT": null,
    "TARO": -9.745,
    "TEVA": 0,
    "PLTK": 11.122,
    "MGIC": -1.756,
    "SMWB": -12.146,
    "PERI": 18.02,
    "GLBE": 6.398,
    "FVRR": 1.534,
    "FORTY": -10.943,
    "CRGO": -10.423,
    "KRNT": -0.909,
    "SEDG": 10.362,
    "PGY": -15.102,
    "HUBC": -49.791,
    "WIX": 0.911,
    "RDWR": 3.975,
    "MNDY": -2.899,
    "RSKD": -4.804,
    "SPNS": 5.462,
    "NICE": 5.867,
    "ALLT": 4.074,
    "ARBE": -24.129,
    "CGNT": 25.532,
    "CHKP": 3.113,
    "WKME": 11.45,
    "CLBT": -2.401,
    "CYBR": -5.085,
    "NVMI": -6.603,
    "CAMT": -8.17,
    "TSEM": 10.128,
    "VLN": -16.258,
    "REE": -15.711,
    "STKH": -13.296,
    "RDCM": -0.156,
    "ELLO": -26.139,
    "ENLT": -0.989,
    "STVN": 17.305,
    "E": 16.711,
    "GNTA": -5.944,
    "ZGN": -0.536,
    "RACE": 6.31,
    "HMC": 3.529,
    "TM": 1.361,
    "MUFG": 4.444,
    "SMFG": 5.83,
    "MFG": 6.429,
    "NMR": 3.533,
    "TAK": 1.46,
    "SONY": 5.51,
    "IX": 6.252,
    "SYT": null,
    "FRHC": 1.434,
    "MLEC": -22.245,
    "ALVO": -28.355,
    "PROC": 2.92,
    "CAAP": 21.925,
    "TS": 1.244,
    "NEXA": 15.315,
    "SPOT": 3.537,
    "GLOB": 4.145,
    "FREY": 8.264,
    "CDRO": 9.742,
    "OEC": 2.497,
    "AMBP": -8.861,
    "TIGO": 13.841,
    "MT": 9.864,
    "TX": 4.92,
    "STBX": 75.789,
    "BANL": null,
    "VCIG": null,
    "CX": 20.884,
    "OMAB": 8.035,
    "PAC": 8.241,
    "VLRS": 12.197,
    "ASR": 4.247,
    "FMX": 5.188,
    "KOF": 10.492,
    "BSMX": 3.721,
    "VIST": 31.474,
    "IBA": -2.203,
    "AMX": 5.268,
    "SIM": 11.063,
    "TV": 16.522,
    "BWMX": 0.088,
    "APXI": 1.444,
    "NETI": 10.162,
    "NMM": 3.609,
    "SB": 8.357,
    "CMRE": 8.547,
    "STNG": 10.126,
    "CLB": 10.391,
    "PHG": 10.504,
    "AEG": 3.002,
    "ING": 9.552,
    "ARGX": 7.105,
    "ALLG": -26.241,
    "STLA": 9.054,
    "QURE": 1.367,
    "PHAR": -6.25,
    "PHVS": 11.111,
    "PRQR": -27.726,
    "MRUS": 18.281,
    "QGEN": -0.517,
    "NXPI": -2.775,
    "ASML": 1.345,
    "VEON": 21.875,
    "IDBA": 28.975,
    "OPRA": 20.867,
    "EQNR": 8.152,
    "CPA": 3.97,
    "BLX": 5.464,
    "BAP": 4.298,
    "IFS": 6.427,
    "CPAC": -2.879,
    "BVN": 0.126,
    "AENZ": -13.284,
    "PHI": -0.375,
    "TDCX": -17.526,
    "KEN": -1.453,
    "KARO": -12.9,
    "GRAB": 4.577,
    "CYD": 4.545,
    "MAXN": 18.711,
    "KLIC": -10.132,
    "APCA": 0.571,
    "CHAA": 0,
    "RFAC": 0.543,
    "MWG": null,
    "FLEX": 2.514,
    "PGRU": 6.195,
    "YY": 7.036,
    "GRIN": -17.541,
    "LITB": 23.529,
    "SE": 5.852,
    "WVE": 9.535,
    "IFN": 3.224,
    "AU": 38.056,
    "GFI": 38.894,
    "HMY": 27.299,
    "DRD": 43.86,
    "SBSW": 5.392,
    "LSAK": -10.56,
    "SSL": 6.08,
    "MX": 1.54,
    "KEP": 10.213,
    "PKX": 28.551,
    "SKM": 0.643,
    "KT": 2.809,
    "DDI": -3.867,
    "GRVY": 10.12,
    "SHG": 1.93,
    "WF": 4.719,
    "KB": -0.245,
    "LPL": 11.594,
    "GRFS": 10.771,
    "SAN": 10.227,
    "BBVA": 9.51,
    "WBX": -17.931,
    "TEF": 13.74,
    "NEON": 1.939,
    "ALV": 2.347,
    "PSNY": -6.475,
    "OTLY": 4.608,
    "CALT": 6.042,
    "OLK": -1.085,
    "ERIC": 10.448,
    "LOGI": 10.943,
    "NVS": 18.35,
    "VECT": 2.472,
    "OCS": 30.347,
    "MLTX": -4.719,
    "MOLN": 6.723,
    "CRSP": 19.608,
    "ACIU": -4.762,
    "ADCT": 4.348,
    "UBS": 10.869,
    "CS": -57.37,
    "GTX": 13.437,
    "GTXAP": 6.411,
    "TEL": 1.465,
    "ABB": 8.08,
    "SOPH": -16.574,
    "ONON": 40.193,
    "CB": 3.31,
    "ALC": 5.915,
    "RIG": 13.518,
    "STM": 3.85,
    "GRMN": 2.281,
    "AMCR": 2.873,
    "GB": -3.583,
    "SRAD": 12.644,
    "PERF": 0.082,
    "GRRR": -66.047,
    "TSM": -1.467,
    "UMC": -2.537,
    "ASX": -3.781,
    "HIMX": -7.653,
    "IMOS": 7.398,
    "CHT": 5.531,
    "GGR": -4.237,
    "HEPS": 29.63,
    "TKC": 10.526,
    "YALA": 0.779,
    "BROG": -8.333,
    "NWTN": 12.936,
    "JHG": 3.142,
    "BCS": 10.745,
    "FDEU": 15.733,
    "BUR": 79.516,
    "AEF": 4.536,
    "EVTL": 37.415,
    "WPP": 4.089,
    "HSBC": 4.61,
    "NWG": 5.255,
    "ADAP": 15.833,
    "CNTA": 4.75,
    "BCYC": -4.605,
    "AUTL": -14.019,
    "DEO": 6.236,
    "ABCM": 12,
    "CCEP": 6.274,
    "LYG": 3.478,
    "EXAI": -23.707,
    "IMCR": 6.765,
    "MREO": 22.353,
    "VRNA": 11.673,
    "TLSA": 116.364,
    "ROIV": 0.235,
    "GSK": 10.556,
    "AZN": 11.594,
    "HLN": 8.5,
    "NVGS": 19.247,
    "TRMD": 2.377,
    "SHEL": 12.537,
    "BP": 13.504,
    "FTI": 5.446,
    "RIO": 6.921,
    "GSM": -0.92,
    "SDRL": 3.352,
    "SNN": 3.634,
    "LIVN": 14.068,
    "CMPS": 16.59,
    "CPRI": 5.76,
    "IHG": 4.484,
    "GSL": 8.613,
    "KNOP": -12.042,
    "FTCH": -6.08,
    "PUK": 11.675,
    "WTW": 4.167,
    "GENI": -6.596,
    "CLVT": -7.865,
    "FERG": 1.562,
    "UL": 8.166,
    "IGT": 10.877,
    "SGHC": 3.836,
    "NVT": 1.346,
    "MANU": -9.434,
    "CNHI": 3.09,
    "AFRI": 0.09,
    "DAVA": -11.468,
    "VTEX": -5.541,
    "ARQQ": 27.835,
    "PSFE": -9.362,
    "PNR": 1.862,
    "LIN": 7.112,
    "RELX": 5.816,
    "RTO": 11.214,
    "ICNC": 0.451,
    "NOMD": 2.816,
    "PSO": 2.155,
    "CWK": -11.08,
    "SLNA": 2.581,
    "LBTYA": 2.435,
    "LBTYK": 2.381,
    "IHS": 28.852,
    "NGG": 7.522,
    "RNW": 16.87,
    "AY": 3.99,
    "VOD": 1.868,
    "BTI": -2.452,
    "ARCO": 1.763,
    "DLO": -0.98,
    "MELI": 8.232
  },
  "additional": {},
  "version": 3
}
