{
  "nodes": {
    "BIOX": -31.912,
    "BBAR": 5.923,
    "BMA": -8.349,
    "GGAL": -5.618,
    "SUPV": 5.142,
    "LOMA": -17.182,
    "CRESY": -23.554,
    "TGS": -9.562,
    "YPF": -16.095,
    "IRS": -19.353,
    "TEO": -19.2,
    "DESP": 13.435,
    "PAM": -11.347,
    "CEPU": -18.449,
    "EDN": -29.766,
    "BHP": -5.583,
    "IONR": -7.048,
    "WDS": -4.87,
    "TBN": 32.054,
    "IREN": -45.996,
    "MESO": 21.679,
    "IMMP": -22.881,
    "OPT": -2.292,
    "TLX": 11.604,
    "NVX": -31.056,
    "OSW": -13.996,
    "NYXH": 30.779,
    "CMBT": -2.053,
    "GLPG": -4.689,
    "TTAM": null,
    "BUD": 20.905,
    "MTLS": -35.547,
    "LBTYA": -8.417,
    "LBTYK": -10.503,
    "BEP": -4.942,
    "VIK": -8.623,
    "BIP": -14.653,
    "NTB": 0.397,
    "DHT": 17.382,
    "CLCO": -21.931,
    "FLNG": 1.726,
    "GLNG": -19.499,
    "NAT": -0.379,
    "TK": 5.769,
    "TNK": 1.169,
    "VAL": -15.415,
    "BORR": -40.933,
    "NBR": -36.048,
    "SDRL": -38.463,
    "BPYPN": 0.47,
    "BPYPO": -3.636,
    "SIG": -43.124,
    "ASC": -11.944,
    "GOGL": -15.401,
    "HSHP": 11.132,
    "SFL": -19.538,
    "HG": 5.781,
    "RNR": -9.414,
    "SPNT": -4.124,
    "AGO": -3.272,
    "AXS": 5.079,
    "ESNT": -1.243,
    "JRVR": -12.061,
    "EG": 0.748,
    "HELE": -23.859,
    "G": 11.685,
    "BNT": -13.667,
    "ESGR": 1.833,
    "FIHL": -20.287,
    "ACGL": 1.286,
    "LND": -1.034,
    "BRFS": -32.842,
    "SUZ": -7.261,
    "CSAN": -15.773,
    "UGP": 0.321,
    "SGML": -0.328,
    "VALE": 3.497,
    "PBR": -3.015,
    "PBR-A": -3.686,
    "BBD": 5.413,
    "INTR": 26.793,
    "ITUB": 13.862,
    "BSBR": 13.265,
    "ABEV": 5.11,
    "LVRO": -20.396,
    "AZUL": -19.824,
    "ERJ": 43.322,
    "VINP": -6.636,
    "XP": 18.015,
    "BAK": -21.457,
    "AFYA": 11.56,
    "VSTA": 62.385,
    "CIG": -0.283,
    "ELPC": 18.787,
    "VIV": 8.213,
    "EBR": 16.396,
    "SBS": 14.249,
    "ELP": 14.913,
    "AMBI": -1.765,
    "TIMB": 17.03,
    "GGB": -13.714,
    "SID": -6.701,
    "PAGS": 17.183,
    "CINT": -1.376,
    "LSPD": -36.353,
    "DCBO": -40.563,
    "DSGX": -16.457,
    "OTEX": -14.328,
    "SHOP": -17.705,
    "QSR": -3.281,
    "POET": -16.632,
    "AG": 6.138,
    "EXK": 10.092,
    "MAG": 5.587,
    "SVM": 26.14,
    "AZ": 3.211,
    "SANG": -29.596,
    "BB": 62.59,
    "TCX": -7.543,
    "TIXT": -31.92,
    "CSIQ": -22.066,
    "TRI": 3.18,
    "ATS": -12.189,
    "BLDP": -19.162,
    "RCI": -17.193,
    "BCE": -8.741,
    "ASTL": -37.327,
    "GFL": 1.825,
    "WCN": 1.655,
    "SUUN": 95.652,
    "TAC": -26.535,
    "FTS": 5.202,
    "TU": -0.987,
    "TFII": -45.91,
    "CCJ": -25.048,
    "DNN": -35.556,
    "NXE": -40.42,
    "UROY": -25.397,
    "AQN": 12.308,
    "TLRY": -48.849,
    "CLS": 2.012,
    "ELVA": 4.348,
    "IMAX": -4.313,
    "STN": -1.076,
    "TGB": 10.599,
    "ACB": 1.152,
    "BHC": -7.124,
    "CGC": -64.024,
    "CRON": -2.564,
    "OGI": -29.605,
    "MEOH": -19.686,
    "ERO": -9.097,
    "HBM": -16.32,
    "TSAT": 35.124,
    "BBU": -9.018,
    "BITF": -46.86,
    "MIST": 28.191,
    "XENE": -17.152,
    "PHYS": 11.138,
    "PSLV": 8.505,
    "SII": -5.139,
    "MGA": -18.446,
    "CAE": 4.207,
    "NTR": 8.918,
    "GIL": -4.097,
    "GOOS": -14.271,
    "LULU": -18.176,
    "BAM": -18.842,
    "BN": -13.772,
    "CEF": 9.834,
    "AUPH": -16.914,
    "CYBN": -25.584,
    "ENGN": -31.6,
    "EPRX": 21.159,
    "VBNK": -35.828,
    "SNDL": -15.301,
    "ABCL": -12.715,
    "ACHV": -31.368,
    "TD": 11.703,
    "RY": -10.568,
    "BMO": -2.69,
    "BNS": -12.679,
    "CM": -15.05,
    "VRN": 25.498,
    "IMO": -5.726,
    "CVE": -11.162,
    "EFXT": -22.407,
    "NOA": -20.313,
    "PBA": 0.231,
    "SOBO": 5.392,
    "SU": -1.363,
    "ENB": 2.74,
    "BTE": -18.077,
    "CNQ": -8.272,
    "GFR": -27.011,
    "VET": -18.172,
    "GTE": -25.83,
    "OBE": -1.622,
    "PDS": -26.714,
    "PROF": -9.801,
    "BLCO": -15.198,
    "VZLA": 24.211,
    "WRN": -2.294,
    "ASM": 62.393,
    "ITRG": 30,
    "MTA": 8.127,
    "MUX": -17.525,
    "NEWP": -16.352,
    "PLG": -17.105,
    "SKE": 14.15,
    "SLI": -14.11,
    "TECK": -6.738,
    "TMC": 126.307,
    "TMQ": 32.5,
    "USAS": 32.829,
    "USGO": -1.541,
    "TRP": 0.951,
    "EMX": 7.345,
    "GRO": -77.179,
    "LAC": -10.386,
    "LGO": -2.709,
    "NAK": 32.519,
    "NMG": 13.571,
    "HITI": -23.585,
    "ADUR": -7.531,
    "CNI": -6.592,
    "CP": -1.064,
    "BRLS": -2.357,
    "SLSR": 8.036,
    "TFPM": 11.346,
    "VOXR": 1.923,
    "BHST": -4.452,
    "CIGI": -15.883,
    "MERC": -4.755,
    "FSV": -11.814,
    "DOOO": -25.536,
    "CIO": -13.471,
    "BRAG": 16.442,
    "AEM": 20.527,
    "AGI": 26.742,
    "ARMN": 10.145,
    "BTG": 14.539,
    "CGAU": -1.645,
    "CNL": 125.066,
    "EGO": -10.151,
    "EQX": 9.048,
    "FNV": 23.809,
    "FSM": 12.524,
    "GAU": 1.449,
    "IAG": 2.534,
    "KGC": 13.826,
    "NFGC": 3.39,
    "NGD": 9.091,
    "ODV": -23.034,
    "OR": 0.149,
    "ORLA": 63.54,
    "PAAS": 11.529,
    "SA": -16.233,
    "SAND": 15.87,
    "THM": 16.961,
    "WPM": 18.689,
    "SLF": -6.949,
    "MFC": -4.476,
    "GIB": -9.165,
    "GLDG": -0.362,
    "GOLD": 8.792,
    "GROY": 18.182,
    "WFG": -16.848,
    "GLRE": -9.549,
    "NU": -3.589,
    "PAX": -8.456,
    "ONC": 43.763,
    "FN": -7.834,
    "CWCO": 12.573,
    "STNE": 11.61,
    "FERAU": null,
    "PLAO": 3.397,
    "CRDO": -32.306,
    "SQM": 13.297,
    "ENIC": 22.261,
    "LTM": 12.33,
    "BSAC": 20.855,
    "BCH": 20.956,
    "CCU": 27.025,
    "AKO-A": 26.9,
    "AKO-B": 22.192,
    "AAPG": null,
    "ANL": 5.14,
    "EH": 64.883,
    "LI": 19.904,
    "LOT": -56.742,
    "NIO": 7.709,
    "NIU": 88.71,
    "NOAH": -4.266,
    "CANG": -6.374,
    "SDA": -46.145,
    "UXIN": -2.691,
    "HSAI": 95.614,
    "KNDI": 51.469,
    "XPEV": 92.025,
    "ZK": 6.29,
    "CAAS": 2.836,
    "ZYBT": null,
    "DAO": 16.074,
    "EDU": -19.582,
    "GOTU": 58.333,
    "TAL": 38.894,
    "HUYA": 43.671,
    "HCAI": null,
    "IQ": 5.957,
    "BILI": 10.133,
    "NTES": 5.253,
    "SOHU": 2.82,
    "BGM": 21.183,
    "FINV": 33.724,
    "LU": 21.293,
    "LX": 76.382,
    "QD": -6.081,
    "QFIN": 23.442,
    "XYF": 57.125,
    "YRD": 61.885,
    "ZLAB": 41.2,
    "NCTY": -32.821,
    "SRL": 10.704,
    "JFIN": 93.13,
    "MOMO": -2.993,
    "NAMI": -24.36,
    "ZH": 36.387,
    "BABA": 65.846,
    "BZUN": 27.372,
    "DADA": 26.351,
    "TME": 10.866,
    "WB": 4.808,
    "JD": 18.32,
    "FLX": -10.164,
    "ZTO": 11.034,
    "ATHM": 11.155,
    "BIDU": 14.434,
    "BZ": 41.27,
    "DOYU": 116.096,
    "DOGZ": -39.466,
    "LANV": 26.923,
    "ATAT": 12.635,
    "GHG": 3.398,
    "HTHT": 12.202,
    "PDD": 24.637,
    "RERE": 15.232,
    "VIPS": 28.52,
    "ZKH": 0.557,
    "PHH": null,
    "YSG": 19.552,
    "LZMH": null,
    "GDS": 70.106,
    "WDH": 22.689,
    "PONY": -2.97,
    "VNET": 181.683,
    "DDL": -23.971,
    "BEKE": 22.331,
    "WYHG": 111.4,
    "EM": 53.553,
    "AHG": 37.939,
    "BDMD": 264.024,
    "ZJYL": 12.964,
    "TCOM": -8.433,
    "TOUR": -0.909,
    "RLX": -1.508,
    "XNET": 117.29,
    "DQ": 7.752,
    "JKS": -15.149,
    "TUYA": 120.67,
    "ZJK": -58.017,
    "MNSO": -7.925,
    "HLP": -4.828,
    "ICG": -27.619,
    "THCH": -8.046,
    "YUMC": 7.806,
    "API": 11.554,
    "NTCL": null,
    "OCFT": 136.364,
    "WRD": 12.563,
    "KC": 94.708,
    "YMM": 18.957,
    "YXT": -59.189,
    "GPRK": -25.743,
    "EC": 23.923,
    "TGLS": -17.587,
    "AVAL": 34.884,
    "CIB": 31.723,
    "GDEV": -18.746,
    "FRO": 11.885,
    "CDLR": -16.688,
    "NVO": -28.239,
    "GMAB": -3.48,
    "ASND": 25.737,
    "NOK": 22.222,
    "AS": 10.637,
    "TTE": 10.498,
    "GNFT": -4.961,
    "IPHA": 19.527,
    "IVA": 12.644,
    "VALN": 76.194,
    "NBTX": -1.471,
    "SNY": 22.776,
    "ABVX": -24.433,
    "CSTM": 4.782,
    "CRTO": -15.947,
    "HKD": -19.113,
    "SAP": 8.023,
    "SHMD": -14.848,
    "ATAI": -1.351,
    "BNTX": -15.485,
    "CVAC": -5.972,
    "DB": 33.874,
    "EVO": -23.617,
    "IMTX": -33.777,
    "NNNN": null,
    "FMS": 1.341,
    "MYTE": 21.348,
    "JMIA": -48.211,
    "SHIP": -1.592,
    "HMR": null,
    "SBLK": 6.705,
    "CCEC": 7.821,
    "DAC": 1.471,
    "DSX": -1.63,
    "ECO": 11.93,
    "ESEA": -5.93,
    "ESEAV": null,
    "GASS": 7.605,
    "DLNG": -12.611,
    "GSL": 5.328,
    "TEN": -5.246,
    "MLCO": -17.385,
    "MSC": -39.182,
    "HTCO": -36.33,
    "FUTU": 36.365,
    "DGNX": null,
    "HCM": -7.002,
    "RGC": 239.45,
    "MCTR": null,
    "LUD": null,
    "ATGL": 164.478,
    "TROO": -48.196,
    "SIMO": -5.022,
    "SIFY": 46.828,
    "MMYT": -19.928,
    "RNW": -17.158,
    "HDB": -8.616,
    "IBN": -4.328,
    "RDY": -8.575,
    "WIT": -15.746,
    "WNS": 28.361,
    "INFY": -20.505,
    "TLK": -13.734,
    "ETN": -17.872,
    "CMPR": -45.547,
    "ALLE": -9.306,
    "ACN": -10.48,
    "DOLE": -3.423,
    "AON": 7.818,
    "AER": 6.531,
    "SW": -15.408,
    "MDT": 12.578,
    "STE": 8.678,
    "PRGO": 3.591,
    "AVDL": -14.341,
    "ALKS": 11.086,
    "AMRN": -11.815,
    "ICLR": -12.447,
    "ADSE": 0.501,
    "TEL": -2.062,
    "JHX": -5.896,
    "JCI": -2.987,
    "TT": -12.294,
    "JAZZ": 16.153,
    "PRTA": -2.898,
    "GHRS": 23.837,
    "RYAAY": 3.935,
    "NEXN": -25.574,
    "ESLT": 46.887,
    "ICL": 23.633,
    "TATT": -0.534,
    "MBLY": -12.207,
    "INVZ": -7.097,
    "REE": -40.65,
    "DRTS": -13.355,
    "CGEN": 1.875,
    "MDWD": 11.312,
    "CSTE": -40.519,
    "NNDM": -7.983,
    "GILT": 16.966,
    "SATX": 48.342,
    "AUDC": 11.702,
    "CRNT": -46.64,
    "TEVA": -4.241,
    "GAUZ": 20.75,
    "PLTK": -42.684,
    "KMDA": 12.026,
    "NNOX": -22.576,
    "ZIM": -3.508,
    "BWAY": 4.077,
    "INMD": -1.45,
    "FVRR": -24.139,
    "GLBE": -33.183,
    "PERI": -3.867,
    "CRGO": 16.495,
    "WILC": 2.062,
    "FORTY": 19.527,
    "MGIC": 12.609,
    "IGIC": 6.311,
    "ITRN": 20.819,
    "ODYS": 5.167,
    "CAMT": -11.697,
    "NVMI": 7.432,
    "TSEM": -20.44,
    "VLN": -4.072,
    "RSKD": -11.765,
    "ALLT": 10.417,
    "ARBE": -25.294,
    "CLBT": -8.485,
    "CYBR": 6.926,
    "MNDY": -4.424,
    "NICE": -17.558,
    "SMWB": -30.441,
    "SPNS": -1.897,
    "WIX": -19.356,
    "SEDG": 20.611,
    "RDWR": -4.287,
    "NYAX": 26.773,
    "ODD": -1.957,
    "CGNT": 3.771,
    "CHKP": 22.483,
    "KRNT": -32.587,
    "RDCM": 1.25,
    "ELLO": 2.28,
    "ENLT": 8.996,
    "STVN": -5.423,
    "E": 9.081,
    "RACE": 1.039,
    "ZGN": -13.45,
    "HMC": 15.086,
    "TM": 5.759,
    "MFG": 13.922,
    "MUFG": 14.168,
    "SMFG": 6.366,
    "TAK": 11.947,
    "SONY": 10.555,
    "NMR": 6.046,
    "IX": -4.263,
    "TOYO": -5.38,
    "KSPI": -7.384,
    "FRHC": 0.606,
    "AGRO": -2.75,
    "CDRO": -4.313,
    "GLOB": -38.363,
    "SPOT": 25.277,
    "TS": -0.768,
    "AUNA": 3.03,
    "AMBP": -9.718,
    "NEXA": -32.506,
    "ALVO": -2.078,
    "CAAP": -4.633,
    "OEC": -23.466,
    "TIGO": 21.641,
    "MT": 23.994,
    "TX": 2.964,
    "AMX": -4.485,
    "SIM": -5.566,
    "BWMX": 0.083,
    "TV": -8.763,
    "OMAB": 12.522,
    "PAC": 3.519,
    "VLRS": -34.977,
    "ASR": 10.677,
    "FMX": 13.126,
    "KOF": 9.743,
    "TBBB": -16.243,
    "CX": 9.369,
    "VTMX": -5.653,
    "VIST": -15.463,
    "STNG": -15.866,
    "NMM": -9.967,
    "SB": -2.584,
    "CMRE": -21.51,
    "FER": 3.104,
    "AEG": 2.978,
    "PHG": 3.033,
    "PLYA": 30.264,
    "CNCK": -50.711,
    "MRUS": 9.331,
    "NAMS": -8.721,
    "QURE": -7.157,
    "PHAR": -5.071,
    "PHVS": -14.992,
    "PRQR": -49.704,
    "QGEN": -13.723,
    "ARGX": 1.373,
    "ING": 29.979,
    "STLA": -9.111,
    "NBIS": -13.697,
    "STM": -3.351,
    "NXPI": -4.553,
    "ASML": 2.226,
    "EQNR": 5.18,
    "OPRA": -6.263,
    "CPA": 3.226,
    "BLX": 7.165,
    "IFS": 13.089,
    "BAP": -2.234,
    "CPAC": -3.866,
    "BVN": 14.937,
    "PHI": 8.27,
    "HPAI": 1.889,
    "CURR": 84.839,
    "RFAI": 1.668,
    "BTDR": -47.416,
    "KARO": -12.278,
    "GRAB": -17.593,
    "KEN": 14.485,
    "HDL": 4.403,
    "YY": 21.3,
    "HAFN": -18.75,
    "UFG": null,
    "BWLP": -6.773,
    "SE": 13.688,
    "GCL": -80.16,
    "EUDA": -21.748,
    "WVE": -34.004,
    "FUFU": -14.63,
    "TIGR": 16.35,
    "CAN": -59.774,
    "AMBR": 72.605,
    "CYD": 145.344,
    "GFI": 38.684,
    "DRD": 33.829,
    "HMY": 28.766,
    "SBSW": -5.324,
    "LSAK": -15.849,
    "SSL": -13.347,
    "KT": 18.286,
    "SKM": -1.05,
    "PKX": 11.074,
    "MX": -6.506,
    "KEP": 3.063,
    "KB": -8.036,
    "SHG": -9.169,
    "WF": 3.239,
    "LPL": 2.83,
    "GRVY": -15.375,
    "DDI": -10.168,
    "GRFS": 5.058,
    "SAN": 41.564,
    "BBVA": 45.783,
    "TEF": 6.306,
    "PSNY": 4.673,
    "ALV": -9.771,
    "NEON": 7.326,
    "ERIC": -0.363,
    "OTLY": -33.145,
    "LAR": -24.342,
    "ALC": 3.8,
    "RIG": -22.494,
    "ONON": -17.423,
    "CB": 7.668,
    "SOPH": -3.614,
    "LOGI": 6.105,
    "OCS": 14.121,
    "MLTX": -27.774,
    "MOLN": -24.181,
    "NVS": 13.159,
    "APTV": 6.385,
    "GES": -19.413,
    "GTX": -3.433,
    "UBS": 3.853,
    "ACIU": -29.167,
    "ADCT": -19.369,
    "CRSP": -10.381,
    "SNRE": 1.048,
    "GB": 20.328,
    "GRMN": -3.773,
    "LAES": 226.957,
    "SRAD": 15.682,
    "PERF": -18.723,
    "ASX": -2.398,
    "IMOS": -3.17,
    "HIMX": 37.761,
    "TSM": -9.435,
    "UMC": 1.669,
    "CHT": 3.041,
    "GGR": -41.397,
    "HEPS": 8.306,
    "TKC": 14.502,
    "MRT": 11.5,
    "YALA": 11.991,
    "MCRP": null,
    "VEON": 23.414,
    "NWTN": -57.259,
    "ECX": 33.333,
    "BCS": 14.359,
    "JHG": -14.985,
    "BUR": -0.434,
    "EVTL": -46.367,
    "WPP": -28.473,
    "CNTA": 0.116,
    "AUTL": -37.241,
    "BCYC": -52.679,
    "ADAP": -28.079,
    "DEO": -13.741,
    "CCEP": 7.443,
    "HSBC": 19.118,
    "LYG": 32.975,
    "NWG": 12.701,
    "GSK": 16.836,
    "AZN": 14.792,
    "HLN": 5.527,
    "KNSA": 8.094,
    "NVT": -24.721,
    "MANU": -21.859,
    "CNH": 10.399,
    "AFRI": -15.331,
    "MREO": -31.688,
    "IMCR": -2.372,
    "VRNA": 66.567,
    "ROIV": -10.405,
    "SLN": -39.535,
    "TLSA": 63.588,
    "MTAL": -18.423,
    "MRX": 10.155,
    "GENI": 2.932,
    "WTW": 5.968,
    "IHG": -10.993,
    "SHCO": 30.584,
    "CPRI": -1.886,
    "CMCL": -0.091,
    "BIRK": -18.246,
    "GAMB": -6.858,
    "IGT": -9.11,
    "SGHC": -0.748,
    "AU": 21.51,
    "PUK": 17.991,
    "CLVT": -21.19,
    "UL": 1.599,
    "SNN": 12.694,
    "CMPS": -23.62,
    "NVCR": -37.07,
    "LIVN": -19.577,
    "SHEL": 8.632,
    "BP": 11.309,
    "CGBS": -6.62,
    "TRMD": -0.57,
    "NVGS": -9.788,
    "KNOP": -6.271,
    "LZM": -34.419,
    "RIO": -2.324,
    "GSM": -6.047,
    "MRNO": -1.026,
    "PSO": 1.904,
    "AMCR": -1.796,
    "NOMD": 11.781,
    "CWK": -29.889,
    "VOD": 12.429,
    "BTI": 10.864,
    "CUK": -22.107,
    "NGG": 6.775,
    "GRRR": 274.112,
    "PSFE": -15.611,
    "RZLV": -12.06,
    "RELX": 4.774,
    "RTO": -17.443,
    "LIN": 4.49,
    "LYB": -1.7,
    "IHS": 17.417,
    "PNR": -20.181,
    "DAVA": -27.389,
    "ARQQ": -1.671,
    "VTEX": -24.398,
    "ARM": -15.221
  },
  "additional": {},
  "subtype": "w13",
  "version": 10,
  "hash": "2227556C5527F8046EE862BAB494921F23F624CE2CCE2FE3D7142596EB8DAF49"
}
