{
  "nodes": {
    "BIOX": -22.982,
    "BBAR": 60.196,
    "BMA": 58.734,
    "GGAL": 88.853,
    "SUPV": 35.417,
    "LOMA": -5.781,
    "CRESY": 15.585,
    "TGS": 45.007,
    "YPF": 91.818,
    "IRS": 64.767,
    "TEO": 15.778,
    "DESP": 3.594,
    "PAM": 48.984,
    "CEPU": 24.641,
    "EDN": 81.325,
    "TEAM": -12.242,
    "WDS": 6.919,
    "IONR": -64.452,
    "BHP": 12.224,
    "DCFC": -88.735,
    "NVX": -63.139,
    "IREN": 8.605,
    "MESO": -45.893,
    "IMMP": 1.309,
    "OPT": -68.087,
    "OSW": 30.571,
    "LHC": 10.477,
    "MTLS": -48.975,
    "NYXH": -18.155,
    "EURN": 0.45,
    "GLPG": -23.217,
    "BUD": 14.641,
    "NTB": -11.603,
    "KNSA": 49.481,
    "LAZ": -10.166,
    "BBU": -29.436,
    "FLNG": -1.204,
    "GLNG": -15.954,
    "DHT": 15.749,
    "TK": 77.035,
    "TNK": 69.655,
    "VAL": 43.668,
    "BORR": 84.197,
    "NBR": 2.652,
    "SDRL": null,
    "SFL": 5.888,
    "SIG": 34.332,
    "ASC": 34.28,
    "CLCO": null,
    "GOGL": -12.544,
    "NAT": 31.544,
    "HSHP": null,
    "G": -20.301,
    "ESGR": 27.155,
    "FIHL": null,
    "IGIC": 43.117,
    "ACGL": 67.436,
    "MHLD": -16.818,
    "RNR": 40.125,
    "SPNT": 112.065,
    "AGO": 13.809,
    "AXS": -0.959,
    "ESNT": 26.51,
    "JRVR": -39.741,
    "WTM": 9.656,
    "BNRE": -12.503,
    "EG": 31.725,
    "ARGO": 47.374,
    "BPYPN": -26.413,
    "BPYPO": -24.948,
    "TGH": 28.915,
    "TRTN": 39.449,
    "BEP": -33.745,
    "BIP": -24.007,
    "LILA": 23.824,
    "LILAK": 24.238,
    "TIMB": 32.631,
    "GGB": 17.541,
    "SID": -7.445,
    "CIG": 9.867,
    "CIG-C": 12.061,
    "ELP": 32.416,
    "VIV": 7.935,
    "EBR": -21.396,
    "EBR-B": -16.558,
    "SBS": 26.169,
    "AMBI": -4.036,
    "SUZ": 15.833,
    "STIX": -46.25,
    "CINT": -29.013,
    "PAGS": -42.418,
    "NTCO": 2.265,
    "VSTA": -17.166,
    "VTRU": -9.551,
    "LND": -6.75,
    "ASAI": -33.348,
    "PBR": 12.121,
    "PBR-A": 14.885,
    "CSAN": -3.934,
    "UGP": 38.023,
    "SGML": 35.735,
    "VALE": 12.121,
    "ATLX": 197.995,
    "BRFS": -42.767,
    "CBD": -36,
    "AFYA": 24.012,
    "ARCE": 0.365,
    "BAK": -21.545,
    "NU": 36.747,
    "INTR": -9.135,
    "ITUB": 9.4,
    "BSBR": -3.513,
    "BBD": -16.152,
    "ABEV": -8.725,
    "LVRO": -31.308,
    "ERJ": 44.206,
    "GOL": -28.389,
    "AZUL": -13.043,
    "VINP": 0.786,
    "PHYS": 11.883,
    "PSLV": 21.24,
    "SII": -11.975,
    "MGA": 1.685,
    "GIL": -7.725,
    "GOOS": -18.167,
    "LULU": 17.66,
    "BAM": null,
    "BN": -12.991,
    "CEF": 13.841,
    "NTR": -30.35,
    "ILLM": -23.721,
    "CAE": 32.999,
    "AUPH": 47.598,
    "BCTX": -20,
    "CYBN": -64.755,
    "VBNK": 3.759,
    "SNDL": -24.419,
    "ABCL": -50.184,
    "ACHV": 3.93,
    "RY": -6.753,
    "TD": -8.948,
    "BMO": -9.581,
    "BNS": -13.9,
    "CM": -17.366,
    "WPRT": -35.849,
    "MEOH": 16.771,
    "HIVE": -21.596,
    "HUT": 22.527,
    "BITF": 0.826,
    "RPTX": -16.733,
    "ONCY": 60,
    "XENE": 1.382,
    "ZYME": 53.118,
    "EPIX": 19.397,
    "FUSN": 0.408,
    "OGI": -61.139,
    "TLRY": -6.211,
    "BHC": 24.317,
    "CGC": -72.674,
    "CRON": -25.676,
    "ACB": -63.007,
    "ERO": 88.069,
    "HBM": 13.447,
    "IE": 45.963,
    "TGB": 26.923,
    "TSAT": 52.143,
    "QBTS": -84.96,
    "NMG": -52.504,
    "EXK": -12.245,
    "GATO": 80.645,
    "MTA": -17.062,
    "MUX": 105.03,
    "NEWP": -8.949,
    "PLG": -16.779,
    "SILV": -19.366,
    "TFPM": 4.077,
    "VOXR": -9.692,
    "VZLA": -23.077,
    "WRN": 9.375,
    "ASM": 12.328,
    "SKE": -4.017,
    "SLI": -41.296,
    "TECK": 23.926,
    "TMC": 16.667,
    "TMQ": -23.376,
    "EMX": -2.094,
    "NAK": 6.482,
    "LAC": -38.573,
    "LGO": -47.276,
    "AMLI": -20.33,
    "PBA": -11.554,
    "ENB": -18.553,
    "IMO": 24.169,
    "SU": 12.668,
    "CVE": 16.544,
    "EFXT": 24.236,
    "NOA": 107.43,
    "WFG": -14.735,
    "PROF": 69.03,
    "BLCO": 9.46,
    "BTE": -9.871,
    "CNQ": 23.597,
    "CPG": 22.56,
    "ERF": 21.086,
    "GTE": -51.679,
    "HHRS": 14.157,
    "OBE": -6.219,
    "VET": -36.156,
    "PDS": 19.388,
    "ZTEK": -30.412,
    "TRX": -18.242,
    "WPM": 31.627,
    "IAG": 73.81,
    "KGC": 39.474,
    "NFGC": 20.809,
    "NG": -12.027,
    "NGD": 48.716,
    "ODV": -38.105,
    "OR": 25.944,
    "ORLA": 33.636,
    "PAAS": 0.85,
    "SA": -11.501,
    "SAND": -14.333,
    "AEM": 11.669,
    "AGI": 60.68,
    "BTG": -9.281,
    "CGAU": 22.609,
    "EGO": 62.264,
    "EQX": 31.339,
    "FNV": 13.494,
    "FSM": 17.797,
    "GAU": 29.63,
    "GLDG": -8.559,
    "GOLD": 3.067,
    "GROY": -51.071,
    "STN": 37.842,
    "LEV": -44.588,
    "IMAX": 20.413,
    "ELVA": -19.037,
    "CLS": 134.774,
    "BRAG": 13.525,
    "ALYA": -18.599,
    "GIB": 29.451,
    "MFC": 7.338,
    "SLF": 9.331,
    "SANG": -50.975,
    "TCX": -54.545,
    "TIXT": -72.46,
    "BB": -19.859,
    "NVEI": -38.65,
    "CSIQ": -44.161,
    "TRI": 15.305,
    "LOOP": -38.333,
    "ATS": 66.076,
    "BLDP": -45.906,
    "SHOP": 103.389,
    "OTEX": 32.047,
    "DCBO": 33.366,
    "DSGX": 7.987,
    "LSPD": -11.036,
    "TRP": -25,
    "MERC": -47.169,
    "HITI": 12.057,
    "CNI": -9.088,
    "CP": 1.568,
    "CIGI": -0.384,
    "REAX": -5.263,
    "TCN": -20.913,
    "DOOO": 10.578,
    "QSR": 13.293,
    "FSV": 22.036,
    "AG": -27.749,
    "MAG": -16.6,
    "SVM": 3.896,
    "POET": -5.411,
    "GFL": 12.036,
    "LICY": -34.192,
    "WCN": -4.583,
    "AQN": -48.253,
    "AQNU": -43.501,
    "FTS": -12.679,
    "TAC": 4.135,
    "TU": -24.899,
    "TFII": 30.65,
    "CCJ": 25.935,
    "DNN": 6.716,
    "NXE": 30.238,
    "UROY": -15.593,
    "BCE": -15.934,
    "PYR": -57.28,
    "ASTL": -20.861,
    "RCI": -7.02,
    "CWCO": 73.188,
    "BCSA": 9.424,
    "PGSS": 10.264,
    "PLAO": null,
    "TGAA": 9.85,
    "GAQ": null,
    "IVCA": null,
    "IVCB": 8.408,
    "STNE": 31.164,
    "GLRE": 34.171,
    "FN": 52.697,
    "FDP": -2.437,
    "XP": 28.262,
    "TBPH": 4.219,
    "BGNE": 17.286,
    "PAX": 3.165,
    "AKO-A": 26.24,
    "AKO-B": 14.356,
    "CCU": 25.623,
    "BCH": 2.013,
    "BSAC": 8.379,
    "ITCL": 1.813,
    "SQM": -43.822,
    "ENIC": 55.026,
    "TCOM": 41.762,
    "TOUR": 70.634,
    "RLX": 13.953,
    "BZ": -35.711,
    "MNSO": 368.246,
    "NAAS": 9.075,
    "DQ": -50.445,
    "JKS": -53.62,
    "MLGO": -77.075,
    "TUYA": 43.333,
    "SOS": -21.788,
    "RTC": -55.22,
    "KC": 105.611,
    "OCFT": -65.922,
    "YMM": -3.324,
    "AIXI": null,
    "API": -38.75,
    "ICG": null,
    "BETS": -74.479,
    "BEKE": -6.404,
    "THCH": -72.881,
    "YUMC": 5.974,
    "YI": -16.561,
    "EM": -1.345,
    "LI": 44.036,
    "NIO": -42.563,
    "NIU": -42.553,
    "PUYI": -0.691,
    "NOAH": -12.976,
    "CANG": -9.578,
    "SDA": 20.717,
    "UCAR": null,
    "KNDI": 55.34,
    "HSAI": null,
    "XPEV": 8.438,
    "CAAS": -3.846,
    "EH": 170.436,
    "XNET": 8.725,
    "HYW": 10.213,
    "SJ": -26.579,
    "YS": -89.641,
    "ZLAB": -42.758,
    "GRCL": 41.593,
    "IMAB": -71.629,
    "TIGR": 39.237,
    "FINV": 15.281,
    "BNR": -64.89,
    "LU": -70.38,
    "LX": 24.868,
    "QD": 102.247,
    "QFIN": 15.055,
    "XYF": 80.932,
    "YRD": 135.849,
    "DAO": -23.684,
    "EDU": 108.691,
    "GOTU": 65.644,
    "IH": 62.358,
    "QSG": null,
    "STG": 100.263,
    "TAL": 32.413,
    "DDL": -58.722,
    "HOLO": 5.743,
    "BILI": -42.591,
    "HOLI": 4.375,
    "IQ": 34.985,
    "NTES": 12.818,
    "SOHU": -44.82,
    "IZM": null,
    "HUYA": -17.915,
    "FANH": 46.502,
    "SFWL": null,
    "ZTO": -5.886,
    "ATHM": -12.241,
    "BIDU": -1.151,
    "DOYU": -36.474,
    "JFIN": 93.98,
    "MOMO": 57.412,
    "TME": 39.579,
    "WB": -28.758,
    "ZH": -20.93,
    "BABA": -0.607,
    "BZUN": -53.866,
    "DADA": -17.23,
    "JD": -45.892,
    "WDH": 15.652,
    "GDS": -51.021,
    "VNET": -31.803,
    "CD": 4.391,
    "SY": 30.494,
    "YSG": -15.741,
    "CNF": 23.134,
    "VIPS": 42.231,
    "GDHG": null,
    "ATAT": null,
    "GHG": 20.802,
    "HTHT": 12.423,
    "RERE": -25.993,
    "LANV": -55.264,
    "YGF": null,
    "EC": 17.408,
    "GPRK": -25.887,
    "EXTO": null,
    "CIB": -8.517,
    "AVAL": -23.208,
    "ESTA": -16.008,
    "TORO": null,
    "FRO": 42.739,
    "GDEV": -54.013,
    "ASND": 7.29,
    "IOBT": -45.161,
    "GMAB": 3.705,
    "NVO": 86.397,
    "NOK": -19.2,
    "SNY": 32.419,
    "NBTX": 126.715,
    "GNFT": -5.238,
    "IPHA": 16.226,
    "IVA": -19.545,
    "VALN": -26.251,
    "CLLS": -46.646,
    "DBVT": -31.111,
    "CRTO": 3.117,
    "CSTM": 36.399,
    "TTE": 32.092,
    "EDAP": -24.029,
    "SQNS": -30.882,
    "HKD": -91.323,
    "ORAN": 14.371,
    "SSU": -90.637,
    "SAP": 64.146,
    "FMS": 24.985,
    "MYTE": -72.864,
    "JMIA": -62.21,
    "TRVG": -23.129,
    "LILM": -54.299,
    "CVAC": -9.816,
    "BNTX": -16.64,
    "ATAI": -66.667,
    "DB": 24.758,
    "IFRX": 66.094,
    "IMTX": -6.236,
    "MOR": 82.16,
    "EVO": 3.431,
    "MYNA": -33.465,
    "CPLP": -4.408,
    "DAC": 2.921,
    "DSX": -21.335,
    "ESEA": 19.706,
    "GASS": 62.583,
    "SBLK": -6.815,
    "TNP": 25.378,
    "TOP": -45.255,
    "HCM": 12.701,
    "RGC": -38.555,
    "FUTU": 30.489,
    "ABLV": null,
    "AMTD": -56.789,
    "TROO": 92.973,
    "SIMO": -26.378,
    "BTWN": 3.552,
    "OPA": 8.014,
    "HHLA": 7.114,
    "MLCO": 94.444,
    "MSC": 325.595,
    "SIFY": 2.899,
    "MMYT": 17.211,
    "YTRA": -13.978,
    "HDB": 1.707,
    "IBN": 4.602,
    "RDY": 26.943,
    "WIT": 1.765,
    "WNS": -22.054,
    "INFY": -3.69,
    "TLK": -19.635,
    "ALLE": 10.306,
    "AER": 38.632,
    "ETN": 67.148,
    "ACN": 13.499,
    "AON": 15.553,
    "ADSE": -10.641,
    "DOLE": 24.062,
    "PDD": 39.366,
    "STE": 9.229,
    "MDT": -8.208,
    "PRGO": -11.754,
    "ALKS": 19.511,
    "AVDL": 117.905,
    "HZNP": 87.249,
    "AMRN": -24.06,
    "STX": -0.381,
    "ICLR": 15.849,
    "JHX": 31.448,
    "JCI": 0.685,
    "TT": 27.802,
    "PRTA": 96.451,
    "CRH": 49.25,
    "JAZZ": -10.263,
    "GHRS": -22.958,
    "RYAAY": 30.043,
    "CMPR": 107.682,
    "APTV": 9.111,
    "ADNT": 16.422,
    "INVZ": -55.11,
    "MBLY": null,
    "TRMR": -51.129,
    "ESLT": -1.834,
    "ICL": -36.383,
    "DRTS": -45.366,
    "GMDA": -50.598,
    "CSTE": -57.426,
    "AUDC": -55.416,
    "CRNT": -11.483,
    "NNDM": 1.493,
    "GILT": 3.226,
    "ITRN": 21.836,
    "SILC": -30.686,
    "KMDA": 10.451,
    "TARO": 16.554,
    "TEVA": 8.824,
    "NNOX": -37.625,
    "INMD": 20.082,
    "ZIM": -63.659,
    "GLBE": 30.479,
    "WILC": -37.954,
    "PLTK": -7.305,
    "SHLT": null,
    "NGMS": 84.47,
    "MGIC": -29.408,
    "NYAX": null,
    "PERI": 60.309,
    "FORTY": -22.642,
    "CRGO": -73.327,
    "FVRR": -15.385,
    "KRNT": -27.602,
    "RDWR": -24.271,
    "SEDG": -52.194,
    "PGY": -76.804,
    "WIX": 43.031,
    "ODD": null,
    "CGNT": -8.56,
    "CHKP": 13.191,
    "RSKD": -7.187,
    "SMWB": -12.062,
    "SPNS": 44.962,
    "ARBE": -64.695,
    "WKME": -9.506,
    "CLBT": 65.895,
    "CYBR": 18.14,
    "NICE": -9.872,
    "MNDY": 45.442,
    "CAMT": 124.745,
    "NVMI": 22.423,
    "TSEM": -38.158,
    "VLN": -41.822,
    "ELLO": -49.261,
    "ENLT": null,
    "RDCM": -26.356,
    "STVN": 79.041,
    "E": 36.071,
    "GNTA": -16.523,
    "ZGN": 38.372,
    "RACE": 52.194,
    "HMC": 30.19,
    "TM": 23.573,
    "MFG": 50.673,
    "SMFG": 60,
    "MUFG": 66.126,
    "NMR": 17.919,
    "TAK": 14.275,
    "IX": 22.755,
    "PXDT": null,
    "SONY": 13.047,
    "SYT": null,
    "FRHC": 63.88,
    "MLEC": -69.238,
    "PROC": -50.649,
    "ALVO": 24.12,
    "CAAP": 103.288,
    "TS": 18.962,
    "AMBP": -45.933,
    "NEXA": 26.111,
    "SPOT": 46.864,
    "GLOB": -2.823,
    "CDRO": 23.045,
    "AGRO": 32.309,
    "FREY": -52.311,
    "TIGO": 14.339,
    "TX": 38.435,
    "MT": 13.781,
    "EVGR": null,
    "VCIG": null,
    "CX": 87.24,
    "OMAB": 73.331,
    "PAC": 20.794,
    "VLRS": 16.457,
    "ASR": 17.859,
    "FMX": 62.833,
    "KOF": 31.622,
    "VIST": 148.749,
    "APXI": null,
    "VTMX": null,
    "SIM": 25.035,
    "AMX": 11.328,
    "BWMX": 102.024,
    "TV": -37.816,
    "CMRE": -6.788,
    "NETI": 34.794,
    "NMM": -14.189,
    "SB": 0,
    "STNG": 24.258,
    "PHG": 24.724,
    "AEG": 9.707,
    "ARGX": 33.896,
    "ING": 57.225,
    "STLA": 37.689,
    "QURE": -61.966,
    "PHAR": 54.867,
    "PHVS": 134.475,
    "PRQR": 92.524,
    "MRUS": -4.327,
    "NAMS": -0.905,
    "QGEN": -9.807,
    "VEON": 66.965,
    "ALLG": -51.392,
    "ASML": 31.715,
    "NXPI": 24.326,
    "ESTC": -6.808,
    "OPRA": 211.878,
    "EQNR": -1.669,
    "CPA": 37.187,
    "BLX": 52.996,
    "IFS": 5.838,
    "BAP": 5.473,
    "CPAC": 5.372,
    "BVN": 40.404,
    "AENZ": -21.52,
    "PHI": -27,
    "FNGR": 693.976,
    "TDCX": -41.952,
    "KEN": -41.591,
    "GRAB": 21.569,
    "KARO": -8.527,
    "MAXN": -29.925,
    "CYD": 38.471,
    "APCA": null,
    "LCAA": 8.121,
    "CHAA": 11.043,
    "CHEA": null,
    "BTDR": 14.385,
    "KLIC": 16.525,
    "FLEX": 45.455,
    "PGRU": -17.417,
    "YY": 26,
    "LITB": 42.901,
    "GRIN": -59.857,
    "SE": -34.982,
    "WVE": 47.403,
    "CAN": -41.304,
    "VFS": 77.169,
    "NCNC": null,
    "AU": 23.834,
    "HMY": 72.5,
    "GFI": 51.046,
    "DRD": 77.656,
    "SBSW": -40.153,
    "SSL": -32.124,
    "LSAK": -27.619,
    "MX": -24.912,
    "KEP": -5.092,
    "PKX": 141.259,
    "KT": -8.459,
    "SKM": -4.248,
    "GRVY": 42.563,
    "DDI": 2.285,
    "HRYU": null,
    "KB": 16.671,
    "WF": 8.566,
    "SHG": 5.551,
    "LPL": -15.587,
    "GRFS": 14.781,
    "SAN": 51.26,
    "BBVA": 67.338,
    "WBX": -68.828,
    "TEF": 3.807,
    "BYNO": null,
    "OTLY": -64.217,
    "CALT": -0.444,
    "ALV": 31.426,
    "PSNY": -59.164,
    "OLK": 1.873,
    "ERIC": -28.988,
    "OCS": 32.924,
    "MLTX": 610.278,
    "MOLN": -12.044,
    "LOGI": 44.348,
    "NVS": 21.497,
    "GTX": 15.303,
    "CRSP": -23.181,
    "ACIU": 12.287,
    "UBS": 64.527,
    "TEL": 1.099,
    "ONON": 51.433,
    "SOPH": -17.822,
    "CB": 5.674,
    "ALC": 21.253,
    "RIG": 129.775,
    "AMCR": -23.554,
    "STM": 22.97,
    "GRMN": 13.27,
    "GB": 10.533,
    "SRAD": 4.244,
    "PERF": -59.718,
    "ASX": 41.953,
    "HIMX": 3.534,
    "IMOS": 15.03,
    "TSM": 12.12,
    "UMC": 9.969,
    "CHT": -7.135,
    "GGR": -32.037,
    "HEPS": 56.566,
    "TKC": 56.977,
    "YALA": 31.122,
    "BROG": -34.249,
    "NWTN": -1.355,
    "ECX": -62.866,
    "JHG": 13.591,
    "BUR": 82.874,
    "EVTL": -66.795,
    "WPP": 11.015,
    "BCS": -3.761,
    "HSBC": 21.692,
    "LYG": -0.493,
    "ADAP": -60.468,
    "ABCM": 60.154,
    "DEO": -8.094,
    "CCEP": 27.664,
    "NWG": -5.5,
    "CNTA": 54.177,
    "BCYC": -17.292,
    "AUTL": 3.03,
    "GSK": 16.069,
    "AZN": 14.042,
    "HLN": 36.068,
    "MTAL": 21.429,
    "MREO": 43.995,
    "ORTX": -4.984,
    "EXAI": -39.956,
    "IMCR": 11.765,
    "ROIV": 262.069,
    "VRNA": 88.857,
    "SLN": -26.586,
    "NVGS": 23.159,
    "TRMD": 26.428,
    "SHEL": 21.096,
    "FTI": 147.703,
    "BP": 26.084,
    "NOMD": -3.678,
    "RIO": 12.682,
    "GSM": -20.623,
    "LZM": 16.766,
    "IHG": 41.447,
    "CPRI": 10.142,
    "KNOP": -57.345,
    "SNN": 2.391,
    "CMPS": -40,
    "LIVN": -2.01,
    "NVCR": -75.833,
    "WTW": -3.534,
    "GENI": 43.111,
    "FTCH": -72.671,
    "PUK": 6.751,
    "CLVT": -42.799,
    "FERG": 33.394,
    "UL": 11.369,
    "CMCL": 3.179,
    "GAMB": 74.967,
    "IGT": 71.693,
    "SGHC": -12.679,
    "AFRI": 6.34,
    "MANU": 37.431,
    "CNHI": 10.82,
    "NVT": 70.793,
    "DAVA": -44.97,
    "VTEX": 36.983,
    "PSFE": -40.972,
    "LIN": 35.329,
    "PNR": 50.653,
    "RELX": 29.621,
    "RTO": 17.883,
    "ICNC": 9.073,
    "IXAQ": null,
    "PSO": 6.099,
    "GSL": 1.224,
    "CWK": -39.169,
    "LBTYA": -9.171,
    "LBTYK": -7.143,
    "IHS": -5.405,
    "NGG": 0.782,
    "RNW": -19.63,
    "AY": -32.585,
    "VOD": -27.708,
    "BTI": -18.36,
    "ARCO": 29.986,
    "DLO": -15.66,
    "MELI": 60.888,
    "SATL": -66.892
  },
  "additional": {},
  "subtype": "w52",
  "version": 5
}
